pyxplod/__version__.py
pyxplod-1.0.0.dist-info/METADATA
pyxplod-1.0.0.dist-info/WHEEL
pyxplod-1.0.0.dist-info/entry_points.txt
pyxplod-1.0.0.dist-info/licenses/LICENSE
pyxplod-1.0.0.dist-info/RECORD
