Metadata-Version: 2.4
Name: pyxplod
Version: 1.0.0
Project-URL: Documentation, https://github.com/twardoch/pyxplod#readme
Project-URL: Issues, https://github.com/twardoch/pyxplod/issues
Project-URL: Source, https://github.com/twardoch/pyxplod
Author-email: Adam Twardoch <adam+github@twardoch.com>
License: MIT
License-File: LICENSE
Classifier: Development Status :: 4 - Beta
Classifier: Intended Audience :: Developers
Classifier: License :: OSI Approved :: MIT License
Classifier: Operating System :: OS Independent
Classifier: Programming Language :: Python
Classifier: Programming Language :: Python :: 3.10
Classifier: Programming Language :: Python :: 3.11
Classifier: Programming Language :: Python :: 3.12
Classifier: Programming Language :: Python :: Implementation :: CPython
Classifier: Programming Language :: Python :: Implementation :: PyPy
Requires-Python: >=3.10
Requires-Dist: fire>=0.7.0
Requires-Dist: loguru>=0.7.2
Requires-Dist: rich>=13.8.0
Provides-Extra: all
Requires-Dist: absolufy-imports>=0.3.1; extra == 'all'
Requires-Dist: fire>=0.7.0; extra == 'all'
Requires-Dist: hatch-vcs>=0.4.0; extra == 'all'
Requires-Dist: hatchling>=1.27.0; extra == 'all'
Requires-Dist: isort>=6.0.1; extra == 'all'
Requires-Dist: loguru>=0.7.2; extra == 'all'
Requires-Dist: mypy>=1.15.0; extra == 'all'
Requires-Dist: myst-parser>=3.0.0; extra == 'all'
Requires-Dist: pre-commit>=4.1.0; extra == 'all'
Requires-Dist: pyupgrade>=3.19.1; extra == 'all'
Requires-Dist: rich>=13.8.0; extra == 'all'
Requires-Dist: ruff>=0.9.7; extra == 'all'
Requires-Dist: sphinx-autodoc-typehints>=2.0.0; extra == 'all'
Requires-Dist: sphinx-rtd-theme>=2.0.0; extra == 'all'
Requires-Dist: sphinx>=7.2.6; extra == 'all'
Provides-Extra: dev
Requires-Dist: absolufy-imports>=0.3.1; extra == 'dev'
Requires-Dist: isort>=6.0.1; extra == 'dev'
Requires-Dist: mypy>=1.15.0; extra == 'dev'
Requires-Dist: pre-commit>=4.1.0; extra == 'dev'
Requires-Dist: pyupgrade>=3.19.1; extra == 'dev'
Requires-Dist: ruff>=0.9.7; extra == 'dev'
Provides-Extra: docs
Requires-Dist: coverage[toml]>=7.6.12; extra == 'docs'
Requires-Dist: myst-parser>=3.0.0; extra == 'docs'
Requires-Dist: pytest-asyncio>=0.25.3; extra == 'docs'
Requires-Dist: pytest-benchmark[histogram]>=5.1.0; extra == 'docs'
Requires-Dist: pytest-cov>=6.0.0; extra == 'docs'
Requires-Dist: pytest-xdist>=3.6.1; extra == 'docs'
Requires-Dist: pytest>=8.3.4; extra == 'docs'
Requires-Dist: sphinx-autodoc-typehints>=2.0.0; extra == 'docs'
Requires-Dist: sphinx-rtd-theme>=2.0.0; extra == 'docs'
Requires-Dist: sphinx>=7.2.6; extra == 'docs'
Provides-Extra: test
Requires-Dist: coverage[toml]>=7.6.12; extra == 'test'
Requires-Dist: pytest-asyncio>=0.25.3; extra == 'test'
Requires-Dist: pytest-benchmark[histogram]>=5.1.0; extra == 'test'
Requires-Dist: pytest-cov>=6.0.0; extra == 'test'
Requires-Dist: pytest-xdist>=3.6.1; extra == 'test'
Requires-Dist: pytest>=8.3.4; extra == 'test'
